geofiles/__init__.py
geofiles/main.py
geofiles/conversion/__init__.py
geofiles/conversion/calculation.py
geofiles/conversion/crs_converter.py
geofiles/conversion/extent_calculation.py
geofiles/conversion/local_converter.py
geofiles/conversion/origin_converter.py
geofiles/conversion/static.py
geofiles/conversion/transformer.py
geofiles/domain/__init__.py
geofiles/domain/face.py
geofiles/domain/file_version.py
geofiles/domain/geo_object.py
geofiles/domain/geo_object_file.py
geofiles/reader/__init__.py
geofiles/reader/base.py
geofiles/reader/city_json_reader.py
geofiles/reader/citygml_reader.py
geofiles/reader/collada_reader.py
geofiles/reader/geo_json_reader.py
geofiles/reader/geo_obj_reader.py
geofiles/reader/geo_off_reader.py
geofiles/reader/geo_ply_reader.py
geofiles/reader/geo_stl_reader.py
geofiles/reader/gml_reader.py
geofiles/reader/json_reader.py
geofiles/reader/kml_reader.py
geofiles/reader/xml_reader.py
geofiles/writer/__init__.py
geofiles/writer/base.py
geofiles/writer/city_json_writer.py
geofiles/writer/citygml_writer.py
geofiles/writer/collada_writer.py
geofiles/writer/geo_json_writer.py
geofiles/writer/geo_obj_writer.py
geofiles/writer/geo_off_writer.py
geofiles/writer/geo_ply_writer.py
geofiles/writer/geo_stl_writer.py
geofiles/writer/geo_vrml_writer.py
geofiles/writer/gml_writer.py
geofiles/writer/json_writer.py
geofiles/writer/kml_writer.py
geofiles/writer/xml_writer.py
geofiles-4.0.0.dist-info/LICENSE
geofiles-4.0.0.dist-info/METADATA
geofiles-4.0.0.dist-info/WHEEL
geofiles-4.0.0.dist-info/top_level.txt
geofiles-4.0.0.dist-info/RECORD
