Metadata-Version: 2.1
Name: geofiles
Version: 4.0.0
Summary: Geofiles is a project for importing and exporting geo-referenced 3D geometry files.
Home-page: https://github.com/FHOOEAIST/geofiles
Author: AIST
Author-email: contact@aist.science
License: UNKNOWN
Project-URL: Bug Tracker, https://github.com/FHOOEAIST/geofiles/issues
Platform: UNKNOWN
Classifier: Programming Language :: Python :: 3
Classifier: License :: OSI Approved :: Mozilla Public License 2.0 (MPL 2.0)
Classifier: Operating System :: OS Independent
Requires-Python: >=3.7
Requires-Dist: pyproj (==3.1.0)
Requires-Dist: attrs (==21.2.0)
Requires-Dist: certifi (==2021.5.30)
Requires-Dist: cjio (==0.6.9)
Requires-Dist: click (==8.0.1)
Requires-Dist: colorama (==0.4.4)
Requires-Dist: jsonref (==0.2)
Requires-Dist: jsonschema (==3.2.0)
Requires-Dist: pyrsistent (==0.18.0)
Requires-Dist: six (==1.16.0)
